{
  "list": [
    {
      "createTime": 1500595200,
      "done": false,
      "id": 0,
      "targetTime": 1500595200,
      "text": "前几天"
    },
    {
      "createTime": 1500911999,
      "done": false,
      "id": 1,
      "targetTime": 1500911999,
      "text": "昨天"
    },
    {
      "createTime": 1500972951,
      "done": false,
      "id": 2,
      "targetTime": 1500972951,
      "text": "早上"
    },
    {
      "createTime": 1500972957,
      "done": false,
      "id": 3,
      "targetTime": 1500972957,
      "text": "中午"
    },
    {
      "createTime": 1500972960,
      "done": false,
      "id": 4,
      "targetTime": 1500972960,
      "text": "晚上"
    }
  ],
  "user": {
    "name": "Rookie_wan"
  }
}